pornhub/__init__.py
pornhub/core.py
pornhub/photos.py
pornhub/stars.py
pornhub/videos.py
pornhub_api_sskender-0.0.1.dist-info/LICENSE
pornhub_api_sskender-0.0.1.dist-info/METADATA
pornhub_api_sskender-0.0.1.dist-info/WHEEL
pornhub_api_sskender-0.0.1.dist-info/top_level.txt
pornhub_api_sskender-0.0.1.dist-info/RECORD
