Metadata-Version: 2.1
Name: pornhub-api-sskender
Version: 0.0.1
Summary: Unofficial API for pornhub.com in Python
Home-page: https://github.com/sskender/pornhub-api
Author: sskender
Author-email: sskender@example.com
License: UNKNOWN
Platform: UNKNOWN
Classifier: Programming Language :: Python :: 3
Classifier: License :: OSI Approved :: MIT License
Classifier: Operating System :: OS Independent
Requires-Python: >=3.6
